behave_web_api/__init__.py
behave_web_api/utils.py
behave_web_api/version.py
behave_web_api/steps/__init__.py
behave_web_api-2.4.0.dist-info/licenses/LICENSE
behave_web_api-2.4.0.dist-info/METADATA
behave_web_api-2.4.0.dist-info/WHEEL
behave_web_api-2.4.0.dist-info/top_level.txt
behave_web_api-2.4.0.dist-info/RECORD
