Metadata-Version: 2.4
Name: behave-web-api
Version: 2.4.0
Summary: Provides testing for JSON APIs with Behave
Home-page: https://github.com/jefersondaniel/behave-web-api
Author: Jeferson Daniel
Author-email: Jeferson Daniel <jeferson.daniel412@gmail.com>
License: MIT
Classifier: Operating System :: OS Independent
Classifier: Development Status :: 5 - Production/Stable
Classifier: Environment :: Web Environment
Classifier: Topic :: Software Development :: Libraries :: Python Modules
Classifier: Topic :: Software Development :: Testing
Classifier: License :: OSI Approved :: MIT License
Classifier: Programming Language :: Python :: 3 :: Only
Classifier: Programming Language :: Python :: 3.11
Classifier: Programming Language :: Python :: 3.12
Requires-Python: >=3.11
License-File: LICENSE
Requires-Dist: behave<2.0.0,>=1.2.6
Requires-Dist: requests>=2.31.0
Provides-Extra: test
Requires-Dist: fastapi==0.110.0; extra == "test"
Requires-Dist: uvicorn==0.23.2; extra == "test"
Requires-Dist: python-multipart==0.0.9; extra == "test"
Requires-Dist: coverage==7.4.4; extra == "test"
Requires-Dist: pytest==8.1.1; extra == "test"
Requires-Dist: pytest-cov==4.1.0; extra == "test"
Dynamic: author
Dynamic: home-page
Dynamic: license-file
Dynamic: requires-python
